pecst/__init__.py
pecst/colors.py
pecst/constants.py
pecst/cost_models.py
pecst/cst_dataclasses.py
pecst/current_capability.py
pecst/dvdt.py
pecst/esr_downloads.py
pecst/functions.py
pecst/generalplotsettings.py
pecst/lifetime.py
pecst/power_loss.py
pecst/read_capacitor_database.py
pecst/selection.py
pecst/foil_capacitor_data/series_values.csv
pecst/foil_capacitor_data/B3271*P/B3271*P.csv
pecst/foil_capacitor_data/B3271*P/B3271*P_derating.csv
pecst/foil_capacitor_data/B3271*P/B3271*P_dvdt.csv
pecst/foil_capacitor_data/B3271*P/B3271*P_lifetime_xV_105degree.csv
pecst/foil_capacitor_data/B3271*P/B3271*P_lifetime_xV_125degree.csv
pecst/foil_capacitor_data/B3271*P/B3271*P_lifetime_xV_85degree.csv
pecst/foil_capacitor_data/B3271*P/B3271*P_self_heating.csv
pecst/foil_capacitor_data/B3272*AGT/B3272*AGT.csv
pecst/foil_capacitor_data/B3272*AGT/B3272*AGT_derating.csv
pecst/foil_capacitor_data/B3272*AGT/B3272*AGT_dvdt.csv
pecst/foil_capacitor_data/B3272*AGT/B3272*AGT_lifetime_xV_105degree.csv
pecst/foil_capacitor_data/B3272*AGT/B3272*AGT_lifetime_xV_125degree.csv
pecst/foil_capacitor_data/B3272*AGT/B3272*AGT_lifetime_xV_135degree.csv
pecst/foil_capacitor_data/B3272*AGT/B3272*AGT_lifetime_xV_85degree.csv
pecst/foil_capacitor_data/B3272*AGT/B3272*AGT_self_heating.csv
pecst/foil_capacitor_data/B3277*P/B3277*P.csv
pecst/foil_capacitor_data/B3277*P/B3277*P_derating.csv
pecst/foil_capacitor_data/B3277*P/B3277*P_dvdt.csv
pecst/foil_capacitor_data/B3277*P/B3277*P_lifetime_630V_105degree.csv
pecst/foil_capacitor_data/B3277*P/B3277*P_lifetime_630V_125degree.csv
pecst/foil_capacitor_data/B3277*P/B3277*P_lifetime_630V_85degree.csv
pecst/foil_capacitor_data/B3277*P/B3277*P_lifetime_630V_95degree.csv
pecst/foil_capacitor_data/B3277*P/B3277*P_lifetime_700V_105degree.csv
pecst/foil_capacitor_data/B3277*P/B3277*P_lifetime_700V_125degree.csv
pecst/foil_capacitor_data/B3277*P/B3277*P_lifetime_700V_85degree.csv
pecst/foil_capacitor_data/B3277*P/B3277*P_lifetime_700V_95degree.csv
pecst-0.1.1.dist-info/METADATA
pecst-0.1.1.dist-info/WHEEL
pecst-0.1.1.dist-info/RECORD
