Metadata-Version: 2.4
Name: pecst
Version: 0.1.1
Summary: Capacitor Selection Toolbox for Power Electroincs.
Project-URL: Homepage, https://github.com/upb-lea/capacitor_selection_toolbox
Project-URL: Issues, https://github.com/upb-lea/capacitor_selection_toolbox/issues
Author: UPB-LEA
Classifier: License :: OSI Approved :: MIT License
Classifier: Operating System :: OS Independent
Classifier: Programming Language :: Python :: 3
Requires-Python: >=3.11
Requires-Dist: matplotlib
Requires-Dist: numpy
Requires-Dist: pandas
Requires-Dist: requests
Requires-Dist: scipy
